MANIFEST.in
README.rst
setup.py
docs/HISTORY.txt
docs/LICENSE.GPL
docs/LICENSE.txt
ftw/__init__.py
ftw.dashboard.dragndrop.egg-info/PKG-INFO
ftw.dashboard.dragndrop.egg-info/SOURCES.txt
ftw.dashboard.dragndrop.egg-info/dependency_links.txt
ftw.dashboard.dragndrop.egg-info/entry_points.txt
ftw.dashboard.dragndrop.egg-info/namespace_packages.txt
ftw.dashboard.dragndrop.egg-info/not-zip-safe
ftw.dashboard.dragndrop.egg-info/requires.txt
ftw.dashboard.dragndrop.egg-info/top_level.txt
ftw/dashboard/__init__.py
ftw/dashboard/dragndrop/__init__.py
ftw/dashboard/dragndrop/configure.zcml
ftw/dashboard/dragndrop/testing.py
ftw/dashboard/dragndrop/browser/__init__.py
ftw/dashboard/dragndrop/browser/configure.zcml
ftw/dashboard/dragndrop/browser/dashboard.py
ftw/dashboard/dragndrop/browser/dashboardEditLinkView.py
ftw/dashboard/dragndrop/browser/foldportlet.py
ftw/dashboard/dragndrop/browser/ftwDashboardPortletManagerRenderer.py
ftw/dashboard/dragndrop/browser/interfaces.py
ftw/dashboard/dragndrop/browser/removeportlet.py
ftw/dashboard/dragndrop/browser/reset.py
ftw/dashboard/dragndrop/browser/updateorder.py
ftw/dashboard/dragndrop/browser/resources/dashboard-compiled.css
ftw/dashboard/dragndrop/browser/resources/dashboard-compiled.js
ftw/dashboard/dragndrop/browser/resources/dashboard.css
ftw/dashboard/dragndrop/browser/resources/dnd_dashboard.js
ftw/dashboard/dragndrop/browser/resources/main.css
ftw/dashboard/dragndrop/browser/resources/main.js
ftw/dashboard/dragndrop/browser/resources/portlet_actions.png
ftw/dashboard/dragndrop/browser/templates/dashboard-column.pt
ftw/dashboard/dragndrop/browser/templates/dashboard.pt
ftw/dashboard/dragndrop/browser/templates/manage-dashboard.pt
ftw/dashboard/dragndrop/locales/ftw.dashboard.dragndrop.pot
ftw/dashboard/dragndrop/locales/plone.pot
ftw/dashboard/dragndrop/locales/de/LC_MESSAGES/ftw.dashboard.dragndrop.po
ftw/dashboard/dragndrop/locales/de/LC_MESSAGES/plone.po
ftw/dashboard/dragndrop/locales/fr/LC_MESSAGES/ftw.dashboard.dragndrop.po
ftw/dashboard/dragndrop/locales/fr/LC_MESSAGES/plone.po
ftw/dashboard/dragndrop/portlets/__init__.py
ftw/dashboard/dragndrop/portlets/configure.zcml
ftw/dashboard/dragndrop/portlets/rss.pt
ftw/dashboard/dragndrop/profiles/default/browserlayer.xml
ftw/dashboard/dragndrop/profiles/default/cssregistry.xml
ftw/dashboard/dragndrop/profiles/default/jsregistry.xml
