Metadata-Version: 2.1
Name: ftw.dashboard.dragndrop
Version: 2.0.0
Summary: ftw.dashboard.dragndrop adds dragndrop functionality to the dashboard
Home-page: https://github.com/4teamwork/ftw.dashboard.dragndrop
Author: 4teamwork AG
Author-email: mailto:info@4teamwork.ch
Maintainer: Mathias Leimgruber
License: GPL2
Keywords: ftw dashboard dragndrop
Platform: UNKNOWN
Classifier: Framework :: Plone
Classifier: Framework :: Plone :: 4.3
Classifier: Framework :: Plone :: 5.1
Classifier: Programming Language :: Python
Classifier: Topic :: Software Development :: Libraries :: Python Modules
Provides-Extra: tests
